advanced_python_hw2_vdaleke/__init__.py
advanced_python_hw2_vdaleke/generate_images.py
advanced_python_hw2_vdaleke/generate_table.py
advanced_python_hw2_vdaleke-0.1.0.dist-info/METADATA
advanced_python_hw2_vdaleke-0.1.0.dist-info/WHEEL
advanced_python_hw2_vdaleke-0.1.0.dist-info/RECORD
