Metadata-Version: 2.3
Name: advanced-python-hw2-vdaleke
Version: 0.1.0
Summary: LaTeX generator
License: MIT
Requires-Python: >=3.12
Classifier: License :: OSI Approved :: MIT License
Classifier: Programming Language :: Python :: 3
Classifier: Programming Language :: Python :: 3.12
Classifier: Programming Language :: Python :: 3.13
